py_dis-0.3.data/scripts/pydisinfo
py_dis-0.3.dist-info/METADATA
py_dis-0.3.dist-info/RECORD
py_dis-0.3.dist-info/WHEEL
py_dis-0.3.dist-info/top_level.txt
pydis/__init__.py
pydis/decoder.py
pydis/formatter.py
pydis/generate_types.py
pydis/instruction.py
pydis/interface.py
pydis/types.py
pydis/zydis_types.py
pydis/lib/libZydis.so
