Metadata-Version: 2.1
Name: py-dis
Version: 0.3
Summary: Python bindings for Zydis library
Home-page: UNKNOWN
Author: Kyle
Author-email: kyle@novogen.org
License: MIT
Platform: UNKNOWN
Classifier: Development Status :: 5 - Production/Stable
Classifier: Intended Audience :: Developers
Classifier: License :: OSI Approved :: MIT License
Classifier: Programming Language :: C
Classifier: Programming Language :: Python :: 3.6
Classifier: Programming Language :: Python :: Implementation :: CPython
Classifier: Topic :: Software Development :: Disassemblers
Classifier: Operating System :: MacOS
Classifier: Operating System :: Unix
Classifier: Operating System :: Microsoft
Requires-Python: >=3.6
